[
  {
    "chinyanja": "Ai",
    "english": "A short form of iai"
  },
  {
    "chinyanja": "Amba",
    "english": "to begin.[see - yamba]."
  },
  {
    "chinyanja": "Ani",
    "english": "what?   What kind?   What sort?"
  },
  {
    "chinyanja": "Anthu",
    "english": "people."
  },
  {
    "chinyanja": "Asamula",
    "english": "to yawn. [see - yasamula]."
  },
  {
    "chinyanja": "Asilikali",
    "english": "soldiers"
  },
  {
    "chinyanja": "Ati",
    "english": "isn't it? Don`t you? (asking for consent) [see also: Eti? Wati?]."
  },
  {
    "chinyanja": "Atsa",
    "english": "to kindle, to light."
  },
  {
    "chinyanja": "Apa",
    "english": "here."
  },
  {
    "chinyanja": "Ba",
    "english": "To steal. [see Kubera]."
  },
  {
    "chinyanja": "Basela",
    "english": "a little extra gift you give to customer who has bought goods from"
  },
  {
    "chinyanja": "Bemberezi",
    "english": "mud wash ."
  },
  {
    "chinyanja": "Birimankhwe",
    "english": "Chameleon."
  },
  {
    "chinyanja": "Bodza",
    "english": "a lie. - Bodza = its a lie!"
  },
  {
    "chinyanja": "Bunda",
    "english": "(pl. Maunda) young bird. young Pigeons, the young of large bird. [see"
  },
  {
    "chinyanja": "Bvaka",
    "english": "to clothe someone, to provide or give clothing.  [see -Bveka]."
  },
  {
    "chinyanja": "Bveka",
    "english": "to clothe someone: to provide or to give clothing."
  },
  {
    "chinyanja": "Bvuma",
    "english": "to give assent, to consent, to take up the chorus (when singing or tell-"
  },
  {
    "chinyanja": "Bvundikila",
    "english": "to cover or to put a lid on."
  },
  {
    "chinyanja": "Bvundukula",
    "english": "to uncover or to take lid off [see - Vundukula]."
  },
  {
    "chinyanja": "Bwebweta",
    "english": "to babble, to stutter, to rave, to be delirious."
  },
  {
    "chinyanja": "Bwerekana",
    "english": "to borrow or to lend to one another."
  },
  {
    "chinyanja": "Bwererana",
    "english": "to come back together again."
  },
  {
    "chinyanja": "Celela",
    "english": "to start off early in the morning. [see - Lawila or Lawilila]."
  },
  {
    "chinyanja": "Chabe",
    "english": "useless. Nothing, only, just."
  },
  {
    "chinyanja": "Chaka",
    "english": "Year or feast."
  },
  {
    "chinyanja": "Chambuyo",
    "english": "backwards."
  },
  {
    "chinyanja": "Chapa",
    "english": "to wash clothes."
  },
  {
    "chinyanja": "Chenjerera",
    "english": "to outwit."
  },
  {
    "chinyanja": "Chenjeretsa",
    "english": "to ask for too high a price, to steal. To want to appear"
  },
  {
    "chinyanja": "Cezela",
    "english": "to visit. - Cezela usiku = to spend the whole night (doing something:"
  },
  {
    "chinyanja": "Uzivelala",
    "english": "= to pay attention to."
  },
  {
    "chinyanja": "Chibvomezi",
    "english": "noise of an earthquake, of a crowd or of dancing."
  },
  {
    "chinyanja": "Chibvundikiro",
    "english": "lid of a pot or container."
  },
  {
    "chinyanja": "Chibwebwe",
    "english": "stuttering, babbling or stammering."
  },
  {
    "chinyanja": "Chibwenzi",
    "english": "friendship - pen pala Cibwenzi."
  },
  {
    "chinyanja": "Chidutswa",
    "english": "a bit cut or broken off something."
  },
  {
    "chinyanja": "Chifwamba",
    "english": "a person who steals, a bandit, a thief.[see Kawalala]."
  },
  {
    "chinyanja": "Chigumula",
    "english": "(1) a flood,(water rising over its banks)."
  },
  {
    "chinyanja": "Chikhulupililo",
    "english": "trust, belief or faith [see - khulupililia]."
  },
  {
    "chinyanja": "Chikumbumtima",
    "english": "memory or rememberance."
  },
  {
    "chinyanja": "Chikwakwa",
    "english": "sickle, reaping-hook, the long hook-knife used as a grass cutter, a"
  },
  {
    "chinyanja": "Chikwanje",
    "english": "a large-bladed knife."
  },
  {
    "chinyanja": "Chilakolako",
    "english": "extreme desire."
  },
  {
    "chinyanja": "Chilankhulo",
    "english": "language."
  },
  {
    "chinyanja": "Chimbudzi",
    "english": "(1) Pit latrine."
  },
  {
    "chinyanja": "Chhimbwira",
    "english": "a person who is not able to children; a woman who is"
  },
  {
    "chinyanja": "Chimwemwe",
    "english": "joy or happiness."
  },
  {
    "chinyanja": "Chinamwail",
    "english": "the dance or ceremony of initiation at puberty. Usually for girls and"
  },
  {
    "chinyanja": "Chinyalala",
    "english": "rubbish, straw, weeds.  [see - Mauzu]."
  },
  {
    "chinyanja": "Chinyontho",
    "english": "moisture [see - mnyontho]."
  },
  {
    "chinyanja": "Chipangano",
    "english": "an agreement, a contract."
  },
  {
    "chinyanja": "Chiphuphu",
    "english": "a bribe."
  },
  {
    "chinyanja": "Chipongwe",
    "english": "rudeness, insolence."
  },
  {
    "chinyanja": "Chithaphwi",
    "english": "a pond."
  },
  {
    "chinyanja": "Chiwerewere",
    "english": "harlotry, wnadering about from one sexual partner to another."
  },
  {
    "chinyanja": "Chiwongo",
    "english": "clan name such as Phiri, Banda, Mbewe,Sakala Mvula."
  },
  {
    "chinyanja": "Chizindikiro",
    "english": "a sign, a mark."
  },
  {
    "chinyanja": "Chizungu",
    "english": "as European in language or manner, but mostly used in reference to"
  },
  {
    "chinyanja": "Coma",
    "english": "to spend the day visiting relatives. Form of greeting from about mid-"
  },
  {
    "chinyanja": "Dekha",
    "english": "to settle (as water), to be calm of mind, to be quiet of heart, gracious"
  },
  {
    "chinyanja": "Dikira",
    "english": "to wait, to wait for. [see - Lindira, Yembekeza]."
  },
  {
    "chinyanja": "Dimba",
    "english": "a garden near water. (Sugar-cane fields mostly grown in dimbas)."
  },
  {
    "chinyanja": "Dongosola",
    "english": "to arrange in order, to do in order, to speak in order. [see longosola]."
  },
  {
    "chinyanja": "Dothi",
    "english": "soil, earth. Mostly used in reference to  rubbish or dirty surroundings."
  },
  {
    "chinyanja": "Dzana",
    "english": "the day before yesterday(can also be refered to as Mazo)."
  },
  {
    "chinyanja": "Dzandidzandzi",
    "english": "the weak or staggering walk of a sick or drunk person."
  },
  {
    "chinyanja": "Dzidzimuka",
    "english": "to be startled."
  },
  {
    "chinyanja": "Enieni",
    "english": "true, truly, really."
  },
  {
    "chinyanja": "Finya",
    "english": "to squeeze, to twist, to press in order to get out pus (in a wound or"
  },
  {
    "chinyanja": "Fumbi",
    "english": "dust.[see - Pfumbi]."
  },
  {
    "chinyanja": "Funkha",
    "english": "to carry off, to remove (in war), to plunder, to carry away everything."
  },
  {
    "chinyanja": "Futsa",
    "english": "to parboil fresh vegetables and then dry them in the sun to preserve"
  },
  {
    "chinyanja": "Guluka",
    "english": "to slip out(e.g. a hoe or an axe from its handle or tooth from its"
  },
  {
    "chinyanja": "Ima",
    "english": "to stop moving, to stand still, to wait, to be in the early months of"
  },
  {
    "chinyanja": "Imika",
    "english": "to put upright, to stand upright."
  },
  {
    "chinyanja": "Imilila",
    "english": "to stand, to stand upright, to stand by, to minister to."
  },
  {
    "chinyanja": "Ipa",
    "english": "to be bad, to be evil, (when one is ugly, one is said to be ‘ipa’ in the"
  },
  {
    "chinyanja": "Ja",
    "english": "Demonstrative stem, for something easily identified or already men-"
  },
  {
    "chinyanja": "Kabvalidwe",
    "english": "manner of dressing or clothes."
  },
  {
    "chinyanja": "Kacetecete",
    "english": "in silence."
  },
  {
    "chinyanja": "Kadendene",
    "english": "heel [see - cidendene]."
  },
  {
    "chinyanja": "Kaikakaika",
    "english": "to doubt."
  },
  {
    "chinyanja": "Kanganula",
    "english": "to loosen."
  },
  {
    "chinyanja": "Kangombwa",
    "english": "a Leophard [see - Nyalubwe, Kaingo(Ns)."
  },
  {
    "chinyanja": "Kankhanta",
    "english": "to beat, to shower with blows upon [see  Kang`antha]."
  },
  {
    "chinyanja": "Kantha",
    "english": "to beat (as cloth in washing), to wash clothes, to beat with your fist,"
  },
  {
    "chinyanja": "Kapompho",
    "english": "(Ns) axe, as Nkhwangwa."
  },
  {
    "chinyanja": "Khala",
    "english": "to remain, to stay,to sit. Also used as an equivalent of ‘li’ = to be, and"
  },
  {
    "chinyanja": "Khapwira",
    "english": "to lap, as an animal when drinking, or when drinking from your hand."
  },
  {
    "chinyanja": "Khatamira",
    "english": "to be wet with rain (body or ground), anything cooked with too much"
  },
  {
    "chinyanja": "Khazikika",
    "english": "to stay in place, to be firmly established, to have settled down, to"
  },
  {
    "chinyanja": "Khotamiro",
    "english": "a Lintel."
  },
  {
    "chinyanja": "Khoza",
    "english": "(1)   to secceed, to do right, to be able to (do something), to manage"
  },
  {
    "chinyanja": "Khululukila",
    "english": "to forgive."
  },
  {
    "chinyanja": "Khulupilila",
    "english": "to trust, to believe, to hope ,to expect, to hope for,  faith.[see Cik hulupililo]. -  (Sometimes) Khulupira = tohave faith."
  },
  {
    "chinyanja": "Khungubwi",
    "english": "a crow [see - khwangala]."
  },
  {
    "chinyanja": "Khwalala",
    "english": "a path, road (wide) as an Elephant path, or a path near a village wid-"
  },
  {
    "chinyanja": "Khwangwala",
    "english": "a Crow [see - Kwawa)"
  },
  {
    "chinyanja": "Khwekhwe",
    "english": "a noose, a trap (for catching birds or rabbits), a snare -  [see Nkwek-"
  },
  {
    "chinyanja": "Khwidzira",
    "english": "to pinion (by binding the arms), to hem, hem in, corner something."
  },
  {
    "chinyanja": "Khwinyata",
    "english": "to shrink, to shrivel up, to dry, to wither (leaves, skin)."
  },
  {
    "chinyanja": "Kolola",
    "english": "(1)   to break something off from above, as maize or  millet from"
  },
  {
    "chinyanja": "Kolowolato",
    "english": "scrape out (ash form a pipe, eye from its socket)."
  },
  {
    "chinyanja": "Kongola",
    "english": "(1) to be beautiful (often used for the beauty of a person,   more intense"
  },
  {
    "chinyanja": "Konola",
    "english": "to pound (used of the first pounding of maize), to break into small"
  },
  {
    "chinyanja": "Kubweleka",
    "english": "to borrow; to lend."
  },
  {
    "chinyanja": "Kubweletsa",
    "english": "to bring."
  },
  {
    "chinyanja": "Kudzichepetsa",
    "english": "to humble oneself."
  },
  {
    "chinyanja": "Kukazinga",
    "english": "to cry."
  },
  {
    "chinyanja": "Kumudwitsa",
    "english": "to give scandal."
  },
  {
    "chinyanja": "outside",
    "english": "[see - Panja]"
  },
  {
    "chinyanja": "Kupempha",
    "english": "to ask for."
  },
  {
    "chinyanja": "Kupemphera",
    "english": "to pray."
  },
  {
    "chinyanja": "Kusula",
    "english": "to propitiate the spirits of the dead (prayer or offering at the grave).[see"
  },
  {
    "chinyanja": "Kusonkhana",
    "english": "to meet or to congregate as a group."
  },
  {
    "chinyanja": "Kutsagana",
    "english": "to accompany each other."
  },
  {
    "chinyanja": "Kutsukuluza",
    "english": "to rinse."
  },
  {
    "chinyanja": "Kuthwawa",
    "english": "to run away."
  },
  {
    "chinyanja": "Kuwanitsa",
    "english": "to be able."
  },
  {
    "chinyanja": "Kwapatira",
    "english": "to put under your arm, to carry under your arm, to cross strings of beads"
  },
  {
    "chinyanja": "Lalika",
    "english": "to proclaim, make known."
  },
  {
    "chinyanja": "Lamba",
    "english": "(1)  belt, girdle."
  },
  {
    "chinyanja": "Lambalala",
    "english": "to skirt, to go around by the side of."
  },
  {
    "chinyanja": "Lilime",
    "english": "tongue [see - lulime]."
  },
  {
    "chinyanja": "Limba",
    "english": "to be hard, firm, strong."
  },
  {
    "chinyanja": "Linthumbu",
    "english": "the red ant [see - Linthumbwi]."
  },
  {
    "chinyanja": "to",
    "english": "pack."
  },
  {
    "chinyanja": "Longosola",
    "english": "to arrange, relate in order, one thing after another"
  },
  {
    "chinyanja": "Luluta",
    "english": "to utter the sound of nthungululu."
  },
  {
    "chinyanja": "Mabuka",
    "english": "eruptions, swelling which come of themselves, on any part of the body,"
  },
  {
    "chinyanja": "Macedzana",
    "english": "(lit.) the year before, the year before last, a long time ago"
  },
  {
    "chinyanja": "Makamaka",
    "english": "especially, surpassing [see - Maka]."
  },
  {
    "chinyanja": "Makangaza",
    "english": "a friut similar to pomegranate."
  },
  {
    "chinyanja": "Makedzana",
    "english": "lit. the year before, the year before last, along time ago."
  },
  {
    "chinyanja": "Makhalidwe",
    "english": "nature, disposition, custom, habit."
  },
  {
    "chinyanja": "Makwerero",
    "english": "a ladder or steps."
  },
  {
    "chinyanja": "Makwinya",
    "english": "wrinkles on eithr clothes or face."
  },
  {
    "chinyanja": "Malonje",
    "english": "what is given for reconcilliation, also an offerring to a visitor as lonjera."
  },
  {
    "chinyanja": "Mancici",
    "english": "a species of a large owl associated with witchcraft."
  },
  {
    "chinyanja": "Manga",
    "english": "(1)  to tie, to bind, fasten, build."
  },
  {
    "chinyanja": "Manja",
    "english": "hands, sing. dzanja."
  },
  {
    "chinyanja": "Mankhaka",
    "english": "cucumbers [see - Makhaka]."
  },
  {
    "chinyanja": "Manthongo",
    "english": "sleep-dust in the corner of the eyes."
  },
  {
    "chinyanja": "Masana",
    "english": "noon, mid-day [see - Mzuwa], but can also be spelled as Msana or"
  },
  {
    "chinyanja": "Maungu",
    "english": "Pumpkins, but Dzungu for one pumpkin, though the seeds are called"
  },
  {
    "chinyanja": "Mbatatase",
    "english": "potatoes."
  },
  {
    "chinyanja": "Mbemberezi",
    "english": "the Ichneunon-fly."
  },
  {
    "chinyanja": "Mbulu",
    "english": "a lump (as in porride), a lump of anything moulded with the hands, a pill"
  },
  {
    "chinyanja": "Mbwemba",
    "english": "the Tamarind tree."
  },
  {
    "chinyanja": "Mdierekezi",
    "english": "a slanderer."
  },
  {
    "chinyanja": "Mdzukulu",
    "english": "grand-child, dscendant, posterity, a younger relation who buries the"
  },
  {
    "chinyanja": "Mfutso",
    "english": "dried vegetable leaves used as ‘ndiwo’ when green  ‘ndiwo’ is not"
  },
  {
    "chinyanja": "Mgwalangwa",
    "english": "the fan palm [see -mlaza]."
  },
  {
    "chinyanja": "Mkamwini",
    "english": "(1)  son-in-law."
  },
  {
    "chinyanja": "Mkandankhuku",
    "english": "brambles."
  },
  {
    "chinyanja": "Mkeka",
    "english": "small basin or pot usually of clay."
  },
  {
    "chinyanja": "Mkokomo",
    "english": "sound of rain; rapids; wind."
  },
  {
    "chinyanja": "Mkombero",
    "english": "a rim; edgeof basket or bicycle."
  },
  {
    "chinyanja": "Mkhunkhu",
    "english": "a club or a stroke [see - Nkhunkhu]."
  },
  {
    "chinyanja": "Mkwapulo",
    "english": "a switch [see - Nkwapulo]."
  },
  {
    "chinyanja": "Mkungudza",
    "english": "a species of tree, used as Cedar."
  },
  {
    "chinyanja": "Mkwingirima",
    "english": "scars of wounds inflicted by a lash."
  },
  {
    "chinyanja": "Mlumbwana",
    "english": "a young man [also - Mulumbwana]."
  },
  {
    "chinyanja": "Mnkhaka",
    "english": "a cucumber (pl) minkhaka or Chidzakaka."
  },
  {
    "chinyanja": "Mnyamata",
    "english": "a boy; a young man; youth."
  },
  {
    "chinyanja": "Mphaka",
    "english": "cat, but sometimes used to refer to a wild cat (a domestic cat is locally"
  },
  {
    "chinyanja": "Mphala",
    "english": "an open shelter where men sit or rest; or to discuss matters or work to-"
  },
  {
    "chinyanja": "Mphambano",
    "english": "at the crossroads."
  },
  {
    "chinyanja": "Mpholopolo",
    "english": "bullet."
  },
  {
    "chinyanja": "Mphulupulu",
    "english": "perverseness."
  },
  {
    "chinyanja": "Mphumphu",
    "english": "wholeness; roundness; perfectness; a ball of tobacco."
  },
  {
    "chinyanja": "Mphunzitsi",
    "english": "teacher."
  },
  {
    "chinyanja": "Mphwando",
    "english": "a big meal; banquet; a feast [see - Phwando]."
  },
  {
    "chinyanja": "Mpingu",
    "english": "a bad omen, i.e seeing a black cat crossing the road in front of you, you"
  },
  {
    "chinyanja": "Mpupuluzi",
    "english": "the scattering of people from the land;deserted land."
  },
  {
    "chinyanja": "Msonkhano",
    "english": "a agathering; a meeting (pl. Masonkhano; Misonkhano)."
  },
  {
    "chinyanja": "Msuanamo",
    "english": "shutting the lips in anger."
  },
  {
    "chinyanja": "Msungwana",
    "english": "girl [see - Mtsikana]."
  },
  {
    "chinyanja": "Mtapo",
    "english": "a place where they dig ore or clay (the clay itself used in the making of"
  },
  {
    "chinyanja": "Mtengatenga",
    "english": "carriage of loads."
  },
  {
    "chinyanja": "Mteteka",
    "english": "a very liquid fermented mealie meal or flour porridge mixed with water."
  },
  {
    "chinyanja": "Mstsekero",
    "english": "(1)   shutting in and so."
  },
  {
    "chinyanja": "Mstempha",
    "english": "a vein; artery; also a tendon."
  },
  {
    "chinyanja": "Mtsibweni",
    "english": "a mother`s elder brother; maternal uncle; head of the family"
  },
  {
    "chinyanja": "Mtswatswa",
    "english": "noise made when walking in the bush; on dry leaves."
  },
  {
    "chinyanja": "Mukangano",
    "english": "objections [see - Kangana]."
  },
  {
    "chinyanja": "Mvundikiro",
    "english": "a lid."
  },
  {
    "chinyanja": "Mwalamwaza",
    "english": "to spread out (flour); turn overr with hand."
  },
  {
    "chinyanja": "Mwamuna",
    "english": "a man; husband."
  },
  {
    "chinyanja": "Mwanbere",
    "english": "swolen glands resulting from wound or sore."
  },
  {
    "chinyanja": "Myuka",
    "english": "to take skin off, to loose the skin."
  },
  {
    "chinyanja": "Mzongo",
    "english": "a strip of meat, as used in drying up biltong; a long narrow piece of"
  },
  {
    "chinyanja": "Mzuli",
    "english": "a fez."
  },
  {
    "chinyanja": "Mzungu",
    "english": "a white man; used to refer to any white person irrespective of origin."
  },
  {
    "chinyanja": "also",
    "english": "-da-."
  },
  {
    "chinyanja": "other",
    "english": "e.g.  ina,   ena. nadzikambe chameleon."
  },
  {
    "chinyanja": "madebvu",
    "english": "a bearded person. ndemanga"
  },
  {
    "chinyanja": "cing'aning'ani",
    "english": "lightning (mamvekera=thunder). -ng'anipa"
  },
  {
    "chinyanja": "Ngwalangwa",
    "english": "a palm-fan."
  },
  {
    "chinyanja": "Ngwandali",
    "english": "hoop iron (from around bales) used as grass slasher."
  },
  {
    "chinyanja": "Nkhadze",
    "english": "a species of Euphoria, a milky juice that causes blindness if it touches"
  },
  {
    "chinyanja": "Nkhalamba",
    "english": "an old person."
  },
  {
    "chinyanja": "Nkhalango",
    "english": "a forest, a thicket; woods."
  },
  {
    "chinyanja": "Nkhanambo",
    "english": "a scab."
  },
  {
    "chinyanja": "Nkhandwe",
    "english": "a Chacal or fox."
  },
  {
    "chinyanja": "Nkholokwa",
    "english": "gleaningsof maize."
  },
  {
    "chinyanja": "Nkhongono",
    "english": "limbs; joints; strength of the body."
  },
  {
    "chinyanja": "Nkhonono",
    "english": "snoring."
  },
  {
    "chinyanja": "Nkhoswe",
    "english": "tutor;advocate;the go-between responsible for marriage agreements."
  },
  {
    "chinyanja": "Nkhukudembo",
    "english": "a turkey."
  },
  {
    "chinyanja": "Nkhulungo",
    "english": "a potter`s stone, used for polishing clay floors of the house."
  },
  {
    "chinyanja": "Nkhungulupsya",
    "english": "burnt grass, particles from bush fire."
  },
  {
    "chinyanja": "Nkhwangwa",
    "english": "axe."
  },
  {
    "chinyanja": "Nkhwende",
    "english": "bark-cloth. [see - Fendaluzi: Mbobvu: Nyanda."
  },
  {
    "chinyanja": "Nkhwekwe",
    "english": "a noose [see - Khwekhwe]."
  },
  {
    "chinyanja": "Nkhwingwirima",
    "english": "scars from stroke of whip [see - Mkwingwirima]."
  },
  {
    "chinyanja": "Nkhwinjiri",
    "english": "leglets or armlets of copper or Iron."
  },
  {
    "chinyanja": "Njenjejenje",
    "english": "ideophone - shivering."
  },
  {
    "chinyanja": "Njenjemera",
    "english": "to shiver or shake with fear or cold."
  },
  {
    "chinyanja": "Nkanagala",
    "english": "musical monochord."
  },
  {
    "chinyanja": "Nkumbalume",
    "english": "one who shoots well."
  },
  {
    "chinyanja": "No",
    "english": "indicates something very near, so near that you are inside it, eg this week,"
  },
  {
    "chinyanja": "Nsakapuka",
    "english": "cattle or dog tick."
  },
  {
    "chinyanja": "Nsambo",
    "english": "brass-wire as leglets or armlets. Token exchanged between two families a"
  },
  {
    "chinyanja": "Nsangamutu",
    "english": "beads for head; head-bands."
  },
  {
    "chinyanja": "Nsanu",
    "english": "sharp pointed grass seeds."
  },
  {
    "chinyanja": "Nsupa",
    "english": "a phial, a bottle."
  },
  {
    "chinyanja": "Nthiwatiwa",
    "english": "an Ostrich."
  },
  {
    "chinyanja": "Nthungulu",
    "english": "shout o joy, shrill trill by women."
  },
  {
    "chinyanja": "Nthunthumira",
    "english": "to tremble or shake with fear."
  },
  {
    "chinyanja": "Nyalanyaza",
    "english": "to be indifferent, inattentive, to sit still when sent anywhere"
  },
  {
    "chinyanja": "Nyankhwa",
    "english": "blunt arrows."
  },
  {
    "chinyanja": "Nyema",
    "english": "to break into pieces, to divide."
  },
  {
    "chinyanja": "Nyemba",
    "english": "bean, sweet bena, long and thin. Kayera is also a type of bean whose"
  },
  {
    "chinyanja": "Nyenyeswa",
    "english": "crumbs."
  },
  {
    "chinyanja": "Nyerenyetsa",
    "english": "to itch, to tickle."
  },
  {
    "chinyanja": "Nyinyirika",
    "english": "grumble or complain. - to despise, to show despite by moving the head, to"
  },
  {
    "chinyanja": "Nyongolotsi",
    "english": "a worm."
  },
  {
    "chinyanja": "Nzandinzandi",
    "english": "weak or staggering walk of a sick or drunk person."
  },
  {
    "chinyanja": "II",
    "english": "to gather and take away, something that is spilled or spread."
  },
  {
    "chinyanja": "Omba",
    "english": "to sound."
  },
  {
    "chinyanja": "Pafupi",
    "english": "near."
  },
  {
    "chinyanja": "Tenga",
    "english": "pakati = become pregnant."
  },
  {
    "chinyanja": "Pakiza",
    "english": "to put in, fill up (a bag)"
  },
  {
    "chinyanja": "Pakuti",
    "english": "because of, since, seeng that -  (also| poti, popeza kuti."
  },
  {
    "chinyanja": "Pala",
    "english": "to plane, to smooth, scrape."
  },
  {
    "chinyanja": "Palamula",
    "english": "to be guilty of, be given a case, to provoke"
  },
  {
    "chinyanja": "Palapata",
    "english": "to be restless"
  },
  {
    "chinyanja": "Palasa",
    "english": "to paddle, row (a boat), to pedal(bicycle) chova"
  },
  {
    "chinyanja": "Pambasuka",
    "english": "to uncoil (piece of string or snake)."
  },
  {
    "chinyanja": "Pamwamba",
    "english": "(Pa) above over upon."
  },
  {
    "chinyanja": "Panikizana",
    "english": "to crowd together, to hustle."
  },
  {
    "chinyanja": "Perekekeza",
    "english": "to accompany, guide."
  },
  {
    "chinyanja": "Pfinya",
    "english": "to press, squeeze, wring out. - chopfinyira = a squeezer."
  },
  {
    "chinyanja": "Pfuula",
    "english": "to shout [see - Fuula]."
  },
  {
    "chinyanja": "Phaphatiza",
    "english": "to force through into a pot, hole or ring."
  },
  {
    "chinyanja": "Phiphiritsa",
    "english": "to speak by allusions, figurative speech."
  },
  {
    "chinyanja": "Phokonyola",
    "english": "to twist off, tear off (a branch, joint neck of fowl]."
  },
  {
    "chinyanja": "Phwanyika",
    "english": "to be broken or smashed. - Cha phwanyika = it has been broken."
  },
  {
    "chinyanja": "Pombedza",
    "english": "to twine around."
  },
  {
    "chinyanja": "Pombonyola",
    "english": "to twist around or off."
  },
  {
    "chinyanja": "Pombosola",
    "english": "to untwist, unwind, disentangle."
  },
  {
    "chinyanja": "Pulula",
    "english": "to strip off, pull off, get off, be carried off (leaves, men)."
  },
  {
    "chinyanja": "Pulupudza",
    "english": "not to obey, to pay no heed, misconduct"
  },
  {
    "chinyanja": "Pwetekere",
    "english": "tomato."
  },
  {
    "chinyanja": "Samba",
    "english": "to bathe or wash oneself, used as euphemism for monthly period of a"
  },
  {
    "chinyanja": "Sokonekera",
    "english": "to be confused, entangled, mixed up."
  },
  {
    "chinyanja": "Sokonombwe",
    "english": "a large grasshopper [see - Tsokonobwe]."
  },
  {
    "chinyanja": "Sonkhanitsa",
    "english": "to gather. - V.T =  call a meeting."
  },
  {
    "chinyanja": "Sonkhezera",
    "english": "to incite, prompt, urge."
  },
  {
    "chinyanja": "Sosa",
    "english": "to hoe lightly, hoe down and gather grass and weeds in preparing a gar-"
  },
  {
    "chinyanja": "Sungaunuka",
    "english": "to melt ( wax: lead: sugar), become watery."
  },
  {
    "chinyanja": "Tafula",
    "english": "to mock at, use filthy language."
  },
  {
    "chinyanja": "Tambalala",
    "english": "to stretch out."
  },
  {
    "chinyanja": "Tambasula",
    "english": "to spread, stretch out, to relax [see - Tambutula]."
  },
  {
    "chinyanja": "Tanganidwa",
    "english": "to be busy."
  },
  {
    "chinyanja": "Tandthauza",
    "english": "to mean, to signify."
  },
  {
    "chinyanja": "Tembenuka",
    "english": "to turn (a complete turn) turn around, to change."
  },
  {
    "chinyanja": "Anatembenuka",
    "english": "=  he has become born again."
  },
  {
    "chinyanja": "Tembenuza",
    "english": "active voice."
  },
  {
    "chinyanja": "Thamanga",
    "english": "to run [see - Thaminga]."
  },
  {
    "chinyanja": "Thima",
    "english": "to be extinguished [see Zima: Zimitsa].- Thimitsa = to extinguish."
  },
  {
    "chinyanja": "spot",
    "english": "- (pl.) Mathotho."
  },
  {
    "chinyanja": "Thumpuka",
    "english": "to float, bob up and down in water."
  },
  {
    "chinyanja": "Tibula",
    "english": "to pound broken maize, the first pounding is ‘Okonola’."
  },
  {
    "chinyanja": "Timba",
    "english": "a species of small birds."
  },
  {
    "chinyanja": "Tipula",
    "english": "to dig or hoe, break up  ground."
  },
  {
    "chinyanja": "Tombosola",
    "english": "to unfold, unwind, unravel."
  },
  {
    "chinyanja": "Tsakamira",
    "english": "to be stuck fast, wedged in"
  },
  {
    "chinyanja": "Tsatsastha",
    "english": "to chop [see - Sasantha]."
  },
  {
    "chinyanja": "Tsazaikana",
    "english": "to separate from, to take leave of."
  },
  {
    "chinyanja": "Tsekemera",
    "english": "to be sweet (sugar-cane, honey).- [see  Tsecemera: Nzuna: Zuna]."
  },
  {
    "chinyanja": "Tsempho",
    "english": "a sickness caused by a woman putting too much salt in ndiwo during her"
  },
  {
    "chinyanja": "day",
    "english": "- (pl.) Masiku - Tsiku lanji ? = what day?"
  },
  {
    "chinyanja": "Tsimphina",
    "english": "to limp."
  },
  {
    "chinyanja": "Tsogoza",
    "english": "front,usually with locatives pa, ku, mu.: Patsogolo, kutsogolo, m`tsogolo."
  },
  {
    "chinyanja": "Tsokomola",
    "english": "to cough."
  },
  {
    "chinyanja": "Tsokonombwe",
    "english": "grass hopper."
  },
  {
    "chinyanja": "Tsukuluka",
    "english": "of a garden, soil that has lost its strength,also of salt."
  },
  {
    "chinyanja": "Tukumuka",
    "english": "to expand, to swell, become larger."
  },
  {
    "chinyanja": "Tulula",
    "english": "to have diarrhea."
  },
  {
    "chinyanja": "Tundumala",
    "english": "to lie heaped together, or a person with her back to the fire"
  },
  {
    "chinyanja": "Ulemerero",
    "english": "glory"
  },
  {
    "chinyanja": "Umbombo",
    "english": "selfishness, miserliness."
  },
  {
    "chinyanja": "Usiwa",
    "english": "shabbiness of clothing."
  },
  {
    "chinyanja": "Vundukula",
    "english": "to uncover [see - Bvundukula]."
  },
  {
    "chinyanja": "Wanda",
    "english": "(1) to lay flat, make level, as levelling grass when walking."
  },
  {
    "chinyanja": "Wanditsa",
    "english": "to make a thing known all around."
  },
  {
    "chinyanja": "Waula",
    "english": "to singe, scorch."
  },
  {
    "chinyanja": "Wawa",
    "english": "(1)  term of great respect, third person plural, for Iwo."
  },
  {
    "chinyanja": "Wawasa",
    "english": "to be sour, to be acidic."
  },
  {
    "chinyanja": "Waza",
    "english": "(1)   to sprinkle, to drizzle."
  },
  {
    "chinyanja": "Wenda",
    "english": "to creep."
  },
  {
    "chinyanja": "Wenga",
    "english": "to peel fruit, to pare."
  },
  {
    "chinyanja": "Werama",
    "english": "to stoop, to bend down."
  },
  {
    "chinyanja": "Weramuka",
    "english": "to get up, raise up from stooping."
  },
  {
    "chinyanja": "Werenga",
    "english": "to read, to count."
  },
  {
    "chinyanja": "Weruka",
    "english": "to leave (e.g work or school) and go."
  },
  {
    "chinyanja": "Weruza",
    "english": "to judge."
  },
  {
    "chinyanja": "Weta",
    "english": "to tend, keep, look after people or cattle."
  },
  {
    "chinyanja": "Weyula",
    "english": "to wave, to turn to one side."
  },
  {
    "chinyanja": "Wina",
    "english": "to win."
  },
  {
    "chinyanja": "Winda",
    "english": "(1)  to protect with medicine."
  },
  {
    "chinyanja": "Winduka",
    "english": "to turn over."
  },
  {
    "chinyanja": "Windula",
    "english": "(1)   to take away medicine protecting house or garden."
  },
  {
    "chinyanja": "Wira",
    "english": "to boil, to bubble."
  },
  {
    "chinyanja": "Wirikiza",
    "english": "to double, to repeat."
  },
  {
    "chinyanja": "Wiringula",
    "english": "to squabble, make excuse for refusing to so something."
  },
  {
    "chinyanja": "Wirira",
    "english": "to be rough with long grass or bush: or hair unshorn."
  },
  {
    "chinyanja": "Wisi",
    "english": "fresh, green."
  },
  {
    "chinyanja": "Wo",
    "english": "their, possessive stem."
  },
  {
    "chinyanja": "Wonga",
    "english": "gun powder."
  },
  {
    "chinyanja": "Wotha",
    "english": "to warm oneself [see  Otha: Othera]."
  },
  {
    "chinyanja": "Ya",
    "english": "to be deep, long (time). - Muyaya = for ever."
  },
  {
    "chinyanja": "Wamuyaya",
    "english": "= eternal."
  },
  {
    "chinyanja": "Yabwa",
    "english": "to itch."
  },
  {
    "chinyanja": "Yaka",
    "english": "to burn, be lit [see -  Yakha]."
  },
  {
    "chinyanja": "Yakha",
    "english": "(1)  to catch (ball)."
  },
  {
    "chinyanja": "Yala",
    "english": "to spread, arrange."
  },
  {
    "chinyanja": "Yaluka",
    "english": "to be insane."
  },
  {
    "chinyanja": "Yamba",
    "english": "to be first, to begin, to provoke."
  },
  {
    "chinyanja": "Yambira",
    "english": "to start (with). - Kuyambira  ... Kufikira = from ... till."
  },
  {
    "chinyanja": "Yambana",
    "english": "to quarrel."
  },
  {
    "chinyanja": "Yambuka",
    "english": "to ford, go across [see - Oloka]."
  },
  {
    "chinyanja": "Yamika",
    "english": "to thank, to praise."
  },
  {
    "chinyanja": "Yamwa",
    "english": "to suck ( breast), suckle."
  },
  {
    "chinyanja": "Yandama",
    "english": "to float."
  },
  {
    "chinyanja": "Yanga",
    "english": "to spread above, to float on water [see - Yangalala]."
  },
  {
    "chinyanja": "Yanika",
    "english": "to spread in the sun to dry."
  },
  {
    "chinyanja": "Yanjana",
    "english": "to be reconciled, to be of one mind."
  },
  {
    "chinyanja": "Yankha",
    "english": "to answer."
  },
  {
    "chinyanja": "Yankhula",
    "english": "to speak, talk [see - Lankhula]."
  },
  {
    "chinyanja": "Yasama",
    "english": "to open the mouth, to gape, to yawn."
  },
  {
    "chinyanja": "Yasamula",
    "english": "to yawn."
  },
  {
    "chinyanja": "Yatsa",
    "english": "to kindle, to light a fire, a candle, a lamp."
  },
  {
    "chinyanja": "Yembekeza",
    "english": "expect [see - Dikira]."
  },
  {
    "chinyanja": "Yenda",
    "english": "to walk, move, travel."
  },
  {
    "chinyanja": "Yendera",
    "english": "to visit."
  },
  {
    "chinyanja": "Yendetsa",
    "english": "to drive, ride, move (something)."
  },
  {
    "chinyanja": "Yenera",
    "english": "must, should, obligation, to fit."
  },
  {
    "chinyanja": "Yenga",
    "english": "to melt fat, tomake oil (from ground-nuts, Castor-beans)."
  },
  {
    "chinyanja": "Yera",
    "english": "to be white, to be clean, to be pure."
  },
  {
    "chinyanja": "Yerekeza",
    "english": "to make like, to compare, to signify."
  },
  {
    "chinyanja": "Yeretsa",
    "english": "to clean."
  },
  {
    "chinyanja": "Yesa",
    "english": "to try, to guess, to measure, to test. -  Mayeso = test, trial, exams."
  },
  {
    "chinyanja": "Yetsemula",
    "english": "to sneeze."
  },
  {
    "chinyanja": "Yokoka",
    "english": "to fall and scatter on the ground (as flowers and seeds)."
  },
  {
    "chinyanja": "Yoyola",
    "english": "to cause to fall and be scattered."
  },
  {
    "chinyanja": "Zama",
    "english": "to be deep, to go right down."
  },
  {
    "chinyanja": "Zambwe",
    "english": "the west wind, the west."
  },
  {
    "chinyanja": "Zaza",
    "english": "to be wild, fierece, to be angry."
  },
  {
    "chinyanja": "Zedi",
    "english": "(adv) very, really, truly (Malawi)."
  },
  {
    "chinyanja": "Zemba",
    "english": "to disappear by getting out of sight, to avoid."
  },
  {
    "chinyanja": "Zenera",
    "english": "a window."
  },
  {
    "chinyanja": "Zenga",
    "english": "to tie, bind round."
  },
  {
    "chinyanja": "Zengereza",
    "english": "to linger, delay, be late (used in confiter?)."
  },
  {
    "chinyanja": "Zerenga",
    "english": "to wrap around, twine around."
  },
  {
    "chinyanja": "Zeze",
    "english": "musical instrument with strings."
  },
  {
    "chinyanja": "Zifuyo",
    "english": "domestic animals, cattle."
  },
  {
    "chinyanja": "Zika",
    "english": "to pierce, put a post into its hole or of a root taking hold"
  },
  {
    "chinyanja": "Zikomo",
    "english": "thank you, please, excuse me."
  },
  {
    "chinyanja": "Zilakolako",
    "english": "eager desires, to covet, lust."
  },
  {
    "chinyanja": "Zima",
    "english": "to be  quenched, be out (a fire, a light) [see - Thima]."
  },
  {
    "chinyanja": "Zimitsa",
    "english": "to quench, extinguish (a fire, a light) [see - Thimitsa]."
  },
  {
    "chinyanja": "Zimbiri",
    "english": "rust [see - Dsimbiri]."
  },
  {
    "chinyanja": "Zimirira",
    "english": "to fade away, become indistinct."
  },
  {
    "chinyanja": "Zindikira",
    "english": "to recognize, understand, realise."
  },
  {
    "chinyanja": "Zinidikiza",
    "english": "to mark, to stamp [see - Tsindika].Zinga"
  },
  {
    "chinyanja": "Zingano",
    "english": "needle + mbota = thread."
  },
  {
    "chinyanja": "Zingwa",
    "english": "to be poor."
  },
  {
    "chinyanja": "Zinyalalala",
    "english": "sweeping, things spread on the ground."
  },
  {
    "chinyanja": "Zinyau",
    "english": "mask of wild beast used in the Nyau dance."
  },
  {
    "chinyanja": "Zira",
    "english": "to smooth by hand with clay, usually using a flat small stone"
  },
  {
    "chinyanja": "Zirala",
    "english": "to be partly quenched (fire or light), of fire or light dying out"
  },
  {
    "chinyanja": "Zitambo",
    "english": "bands of plaited grass worn around head by women after  the death of"
  },
  {
    "chinyanja": "Ziwanda",
    "english": "evil spirits [see - Chiwanda: Zithumwa]."
  },
  {
    "chinyanja": "Ziwiya",
    "english": "household utensils."
  },
  {
    "chinyanja": "Ziya",
    "english": "to be exhausted, faint [see - Lefuka]."
  },
  {
    "chinyanja": "Zizira",
    "english": "to be cool, to be cold, to be insipid, without savour, to be calm."
  },
  {
    "chinyanja": "Ziziritsa",
    "english": "to chill, make cold, to be very cold."
  },
  {
    "chinyanja": "Zizwa",
    "english": "to be astonished [see - Dodoma]."
  },
  {
    "chinyanja": "Zokota",
    "english": "to engrave, to carve, make embroidery [see - Zukuta]."
  },
  {
    "chinyanja": "Zolika",
    "english": "to bend down the head, to be ashamed. - [see - Jolika: Zyolika]."
  },
  {
    "chinyanja": "Zoloweera",
    "english": "to be accustomed to ."
  },
  {
    "chinyanja": "Zoloweza",
    "english": "to accustom."
  },
  {
    "chinyanja": "Zonda",
    "english": "to spy, to look around."
  },
  {
    "chinyanja": "Zonga",
    "english": "to cut meat in long strips [see - Zyonga]."
  },
  {
    "chinyanja": "Zuka",
    "english": "to come out, be uprooted."
  },
  {
    "chinyanja": "Zukuta",
    "english": "carve wood/Ivory embroider [see - Zokota]."
  },
  {
    "chinyanja": "Zula",
    "english": "to pull up with the roots, to pull off (a peg, a nail)."
  },
  {
    "chinyanja": "Zuna",
    "english": "to be sweet [see Nzuna: Tsemera]."
  },
  {
    "chinyanja": "Zungulira",
    "english": "to surround, go around."
  },
  {
    "chinyanja": "Zunguza",
    "english": "to whilr around."
  },
  {
    "chinyanja": "Zungunyula",
    "english": "to sprain, twist [see – Dzungunyula: Dzungunyula]."
  },
  {
    "chinyanja": "Zunza",
    "english": "to afflict, make suffer, annoy. -  Mazunzo = suffering."
  },
  {
    "chinyanja": "Zunzika",
    "english": "to be afflicted, to suffer."
  },
  {
    "chinyanja": "Zweta",
    "english": "to wheel round."
  },
  {
    "chinyanja": "Zyolika",
    "english": "to hold one`s head down, to be ashamed [see         ]"
  }
]